longbridge-0.2.77.dist-info/METADATA
longbridge-0.2.77.dist-info/WHEEL
longbridge/py.typed
longbridge/openapi.py
longbridge/__init__.py
longbridge/openapi.pyi
longbridge/longbridge.cpython-39-aarch64-linux-gnu.so
longbridge-0.2.77.dist-info/RECORD
