Metadata-Version: 2.1
Name: longbridge
Version: 0.2.77
Classifier: Development Status :: 3 - Alpha
Classifier: Intended Audience :: Developers
Classifier: Topic :: Office/Business :: Financial
Classifier: Programming Language :: Rust
Classifier: Programming Language :: Python :: Implementation :: CPython
Summary: A Python library for Longbridge Open API
Keywords: longbridge,openapi,sdk
Home-Page: https://open.longbridgeapp.com/en/
License: MIT OR Apache-2.0
Project-URL: changelog, https://github.com/longbridgeapp/openapi-sdk/blob/master/python/CHANGELOG.md
Project-URL: repository, https://github.com/longbridgeapp/openapi-sdk
Project-URL: documentation, https://open.longbridgeapp.com/en/docs
Project-URL: homepage, https://open.longbridgeapp.com/en/
